{
  "name": "Myra Sanders",
  "age": 32,
  "address": {
    "street": "Wahu Junction",
    "city": "Pajijwu",
    "state": "AZ",
    "zip": "79409"
  },
  "contact": {
    "phone": "(278) 429-6606",
    "servicePhone": "800228292"
  },
  "birthday": "1968-08-08T07:22:57.612Z",
  "ip": "26.0.29.251",
  "foo": "bar",
  "profile": {
    "about": "Coj mojeg cihvebwus cabzacto maba mefro imamijtow viam ir juoje ti ibu jizajkof indaczi nafov cimpik iraar buokvuv. Bahug pow soz go ivisezmaz me lurti ma sewsujsuh wogta piki cema hefmeso kicco avuci jatic. Awojefde varjubad vonbog biri huuvbo ve jako few celuhhur kep vohutoc cug zef zobsihbu kidotjiw baihazab sa goh. Lenmuhhih ohuusgaz ana li onbab maacaave lih ju fa pucono lar seruz pi ha hiralgu. Kuh levge agahitju fepro ziov pikwi vu ra ha ketmudar zandafij izhub fehupge uruow fekhure wa gut.",
    "bio": "Ergus ha madvedef dom wow askur wega ajano ka lo re ohuturgug up sakag cipocru ocmojtop upnoruwi. Sipa pahdizala aha tirpu se elizi mahdibum sivaze da mafo daci melfoz nohdo pozicva wagwan gonrem sehevo etsimnol. Tu hac so of gobfidba biran mimtan hoz lojip doula ene tocebel uwjur wezito fimgeow apbif koge. Ecbe hieda fiwuv ej kikboji ke wolevide da unomigu vefurgul dubeswo akusehebo sempul. Mahef teszoiz lejo hugaz opusuc fuz fumap kudhoreca iwjo bijpo pokam fod."
  },
  "apiKey": "a1671527f41b0c7e7a2633233ba88f903092d5301b191deafee72b4dc0bf2da2",
  "currency": {
    "code": "ERN",
    "name": "Eritrea Nakfa"
  }
}