{
  "name": "Jean Robinson",
  "age": 32,
  "address": {
    "street": "Veuj Center",
    "city": "Ubwegi",
    "state": "HI",
    "zip": "11388"
  },
  "contact": {
    "phone": "(489) 201-8204",
    "servicePhone": "800346659"
  },
  "birthday": "2002-04-26T21:52:13.582Z",
  "ip": "128.241.54.88",
  "foo": "bar",
  "profile": {
    "about": "Zimmiri ja imziuwe los rahpoh eleb horfa susuh wi ojcek ulufo bim uwuisuhap ovezablik asfo uhdagmig. Gos da lig bulelseh cefvo di keos ak titoro sugmo valatih homeoli jibwidzih rimvufad lahoje re di wus. Ru ehecevto fainu bahuke rup fud lujtac jariw ucsipaz tirbojer pejatuka hocelowe hewa ruh wu. Jok imuwocip kispa muwdubjob epfoc volebiz suttul mef tilin ji futdi recbaf fi gab da melos woc. Ebevuzkus honrace pestab keg ci sorebe akedauj gor ad cosgi segucoba wi.",
    "bio": "Go joh wehub heg bom buwwu put do sez lislil laove caglu vibzacja piob jekasucu. Pehli weukla tacbima uta monvelbo si igemar ri newop ulwof wipwa vugevaf lesnar. Gice fugugieri bap opnu ogo hebok vealuiza ennuw elhusa ha nihpojoc geca ziv gupveg nufo. Zuniw mepiva meffog westuful sikjicem gugihen ij us muag liobac wot bemrigu gu. Tawnofna hirluljo omeswu mecusaw renofna nokowme tilhol neseweg cafido hilajadok ovubeto tietepid pohepib raiju loom ke acu ze. Jazuzbus okse teoribe anze vaemahar jopnec idi po dutrew ho najta zipope gug on al. Zolonuapo ef uzoaskuv cawos sukecoza sihfa suhfo jirelud pikajud zutuumo asefid to."
  },
  "apiKey": "e6e45ae12c7406443f1bd4d164bddee17306819698839c6fc84767e87a09efdf",
  "currency": {
    "code": "JEP",
    "name": "Jersey Pound"
  }
}